distance_metrics_mcda/__init__.py
distance_metrics_mcda/additions.py
distance_metrics_mcda/correlations.py
distance_metrics_mcda/distance_metrics.py
distance_metrics_mcda/normalizations.py
distance_metrics_mcda/weighting_methods.py
distance_metrics_mcda/mcda_methods/__init__.py
distance_metrics_mcda/mcda_methods/mcda_method.py
distance_metrics_mcda/mcda_methods/topsis.py
distance_metrics_mcda-0.0.5.dist-info/LICENSE
distance_metrics_mcda-0.0.5.dist-info/METADATA
distance_metrics_mcda-0.0.5.dist-info/WHEEL
distance_metrics_mcda-0.0.5.dist-info/top_level.txt
distance_metrics_mcda-0.0.5.dist-info/RECORD
