Metadata-Version: 2.1
Name: distance-metrics-mcda
Version: 0.0.5
Summary: Package for Multi-Criteria Decision Analysis with distance-based TOPSIS method
Home-page: https://github.com/energyinpython/distance-metrics-for-mcda
Author: Aleksandra Ba
Author-email: aleksandra.baczkiewicz@phd.usz.edu.pl
License: UNKNOWN
Platform: UNKNOWN
Classifier: Programming Language :: Python :: 3
Classifier: License :: OSI Approved :: MIT License
Classifier: Operating System :: OS Independent
Requires-Python: >=3.4
License-File: LICENSE
Requires-Dist: numpy
